{
	"configurations" : 
	[
		{
			"directories" : 
			[
				{
					"build" : ".",
					"jsonFile" : "directory-.-Debug-f5ebdc15457944623624.json",
					"minimumCMakeVersion" : 
					{
						"string" : "3.22"
					},
					"projectIndex" : 0,
					"source" : ".",
					"targetIndexes" : 
					[
						0
					]
				}
			],
			"name" : "Debug",
			"projects" : 
			[
				{
					"directoryIndexes" : 
					[
						0
					],
					"name" : "Scheduling_Algorithm",
					"targetIndexes" : 
					[
						0
					]
				}
			],
			"targets" : 
			[
				{
					"directoryIndex" : 0,
					"id" : "Scheduling_Algorithm::@6890427a1f51a3e7e1df",
					"jsonFile" : "target-Scheduling_Algorithm-Debug-700bc95ae3005d73e69b.json",
					"name" : "Scheduling_Algorithm",
					"projectIndex" : 0
				}
			]
		}
	],
	"kind" : "codemodel",
	"paths" : 
	{
		"build" : "/home/kroking/CLionProjects/Scheduling-Algorithm/cmake-build-debug",
		"source" : "/home/kroking/CLionProjects/Scheduling-Algorithm"
	},
	"version" : 
	{
		"major" : 2,
		"minor" : 3
	}
}
